[
    {
      "id": 1,
      "phrase": "El éxito es la suma de pequeños esfuerzos repetidos día tras día.",
      "author": "Robert Collier"
    },
    {
      "id": 2,
      "phrase": "La única forma de hacer un gran trabajo es amar lo que haces.",
      "author": "Steve Jobs"
    },
    {
      "id": 3,
      "phrase": "No te preocupes por los fracasos, preocúpate por las oportunidades que pierdes cuando no lo intentas.",
      "author": "Jack Canfield"
    },
    {
      "id": 4,
      "phrase": "El futuro pertenece a aquellos que creen en la belleza de sus sueños.",
      "author": "Eleanor Roosevelt"
    },
    {
      "id": 5,
      "phrase": "Cree que puedes y ya estarás a medio camino.",
      "author": "Theodore Roosevelt"
    }
  ]
  